{
  "_comment": "Experiment 4 - Maze: 100x100-Grid mit zentralem Nest und mehreren Nahrungsquellen hinter Labyrinthwaenden. Mehr Ameisen verbessern die parallele Suche, verursachen aber Staueffekte in schmalen Korridoren.",
  "experiment": {
    "id": "exp4_maze_30x30_fair_convergent",
    "name": "Experiment 4: Maze 30x30 (Fair Convergent)",
    "description": "Konvergenz ohne Nest-Nahe-Food: entfernte Nahrungsquellen, moderate Pheromonparameter, reduzierte Population und zwei zusaetzliche mittlere Korridor-Verbindungen.",
    "max_ticks": 3000,
    "warmstart": false
  },
  "item_types": [
    {
      "id": "food",
      "name": "Nahrung",
      "evaporation_rate": 0.0
    },
    {
      "id": "pheromone_nest",
      "name": "Nest-Pheromon",
      "evaporation_rate": 0.004
    },
    {
      "id": "pheromone_food",
      "name": "Nahrung-Pheromon",
      "evaporation_rate": 0.004
    }
  ],
  "agent_types": [
    {
      "id": "ant",
      "name": "Ameise",
      "energy": 2200,
      "perception_range": 4,
      "pheromone_drop_amount": 40.0,
      "capacity": [
        {
          "item_type_id": "food",
          "max": 1
        },
        {
          "item_type_id": "pheromone_nest",
          "max": -1
        },
        {
          "item_type_id": "pheromone_food",
          "max": -1
        }
      ]
    }
  ],
  "spawns": [
    {
      "id": "nest_main",
      "name": "Hauptnest",
      "agent_spawns": [
        {
          "agent_type_id": "ant",
          "count": 40
        }
      ]
    }
  ],
  "grid": {
    "width": 30,
    "height": 30,
    "default_capacity": 0,
    "fields": [
      {
        "x": 1,
        "y": 1,
        "capacity": 5,
        "items": []
      },
      {
        "x": 2,
        "y": 1,
        "capacity": 5,
        "items": []
      },
      {
        "x": 3,
        "y": 1,
        "capacity": 5,
        "items": []
      },
      {
        "x": 4,
        "y": 1,
        "capacity": 5,
        "items": []
      },
      {
        "x": 5,
        "y": 1,
        "capacity": 5,
        "items": []
      },
      {
        "x": 6,
        "y": 1,
        "capacity": 5,
        "items": []
      },
      {
        "x": 7,
        "y": 1,
        "capacity": 5,
        "items": [
          {
            "item_type_id": "food",
            "quantity": 160
          }
        ]
      },
      {
        "x": 8,
        "y": 1,
        "capacity": 5,
        "items": []
      },
      {
        "x": 9,
        "y": 1,
        "capacity": 5,
        "items": []
      },
      {
        "x": 10,
        "y": 1,
        "capacity": 5,
        "items": []
      },
      {
        "x": 11,
        "y": 1,
        "capacity": 5,
        "items": []
      },
      {
        "x": 12,
        "y": 1,
        "capacity": 5,
        "items": []
      },
      {
        "x": 13,
        "y": 1,
        "capacity": 5,
        "items": []
      },
      {
        "x": 15,
        "y": 1,
        "capacity": 5,
        "items": []
      },
      {
        "x": 16,
        "y": 1,
        "capacity": 5,
        "items": []
      },
      {
        "x": 17,
        "y": 1,
        "capacity": 5,
        "items": []
      },
      {
        "x": 18,
        "y": 1,
        "capacity": 5,
        "items": []
      },
      {
        "x": 19,
        "y": 1,
        "capacity": 5,
        "items": []
      },
      {
        "x": 20,
        "y": 1,
        "capacity": 5,
        "items": []
      },
      {
        "x": 21,
        "y": 1,
        "capacity": 5,
        "items": []
      },
      {
        "x": 22,
        "y": 1,
        "capacity": 5,
        "items": []
      },
      {
        "x": 23,
        "y": 1,
        "capacity": 5,
        "items": []
      },
      {
        "x": 24,
        "y": 1,
        "capacity": 5,
        "items": []
      },
      {
        "x": 25,
        "y": 1,
        "capacity": 5,
        "items": []
      },
      {
        "x": 26,
        "y": 1,
        "capacity": 5,
        "items": []
      },
      {
        "x": 27,
        "y": 1,
        "capacity": 5,
        "items": []
      },
      {
        "x": 1,
        "y": 2,
        "capacity": 5,
        "items": []
      },
      {
        "x": 13,
        "y": 2,
        "capacity": 5,
        "items": []
      },
      {
        "x": 15,
        "y": 2,
        "capacity": 5,
        "items": []
      },
      {
        "x": 25,
        "y": 2,
        "capacity": 5,
        "items": []
      },
      {
        "x": 27,
        "y": 2,
        "capacity": 5,
        "items": []
      },
      {
        "x": 1,
        "y": 3,
        "capacity": 5,
        "items": [
          {
            "item_type_id": "food",
            "quantity": 170
          }
        ]
      },
      {
        "x": 3,
        "y": 3,
        "capacity": 5,
        "items": []
      },
      {
        "x": 4,
        "y": 3,
        "capacity": 5,
        "items": []
      },
      {
        "x": 5,
        "y": 3,
        "capacity": 5,
        "items": []
      },
      {
        "x": 6,
        "y": 3,
        "capacity": 5,
        "items": []
      },
      {
        "x": 7,
        "y": 3,
        "capacity": 5,
        "items": []
      },
      {
        "x": 8,
        "y": 3,
        "capacity": 5,
        "items": []
      },
      {
        "x": 9,
        "y": 3,
        "capacity": 5,
        "items": []
      },
      {
        "x": 10,
        "y": 3,
        "capacity": 5,
        "items": []
      },
      {
        "x": 11,
        "y": 3,
        "capacity": 5,
        "items": []
      },
      {
        "x": 12,
        "y": 3,
        "capacity": 5,
        "items": []
      },
      {
        "x": 13,
        "y": 3,
        "capacity": 5,
        "items": [
          {
            "item_type_id": "food",
            "quantity": 150
          }
        ]
      },
      {
        "x": 15,
        "y": 3,
        "capacity": 5,
        "items": []
      },
      {
        "x": 17,
        "y": 3,
        "capacity": 5,
        "items": []
      },
      {
        "x": 18,
        "y": 3,
        "capacity": 5,
        "items": []
      },
      {
        "x": 19,
        "y": 3,
        "capacity": 5,
        "items": []
      },
      {
        "x": 20,
        "y": 3,
        "capacity": 5,
        "items": []
      },
      {
        "x": 21,
        "y": 3,
        "capacity": 5,
        "items": []
      },
      {
        "x": 23,
        "y": 3,
        "capacity": 5,
        "items": []
      },
      {
        "x": 24,
        "y": 3,
        "capacity": 5,
        "items": []
      },
      {
        "x": 25,
        "y": 3,
        "capacity": 5,
        "items": []
      },
      {
        "x": 27,
        "y": 3,
        "capacity": 5,
        "items": []
      },
      {
        "x": 3,
        "y": 4,
        "capacity": 5,
        "items": []
      },
      {
        "x": 15,
        "y": 4,
        "capacity": 5,
        "items": []
      },
      {
        "x": 17,
        "y": 4,
        "capacity": 5,
        "items": []
      },
      {
        "x": 23,
        "y": 4,
        "capacity": 5,
        "items": []
      },
      {
        "x": 27,
        "y": 4,
        "capacity": 5,
        "items": []
      },
      {
        "x": 1,
        "y": 5,
        "capacity": 5,
        "items": []
      },
      {
        "x": 2,
        "y": 5,
        "capacity": 5,
        "items": []
      },
      {
        "x": 3,
        "y": 5,
        "capacity": 5,
        "items": []
      },
      {
        "x": 5,
        "y": 5,
        "capacity": 5,
        "items": []
      },
      {
        "x": 6,
        "y": 5,
        "capacity": 5,
        "items": []
      },
      {
        "x": 7,
        "y": 5,
        "capacity": 5,
        "items": []
      },
      {
        "x": 8,
        "y": 5,
        "capacity": 5,
        "items": []
      },
      {
        "x": 9,
        "y": 5,
        "capacity": 5,
        "items": []
      },
      {
        "x": 10,
        "y": 5,
        "capacity": 5,
        "items": []
      },
      {
        "x": 11,
        "y": 5,
        "capacity": 5,
        "items": []
      },
      {
        "x": 12,
        "y": 5,
        "capacity": 5,
        "items": []
      },
      {
        "x": 13,
        "y": 5,
        "capacity": 5,
        "items": []
      },
      {
        "x": 15,
        "y": 5,
        "capacity": 5,
        "items": []
      },
      {
        "x": 16,
        "y": 5,
        "capacity": 5,
        "items": []
      },
      {
        "x": 17,
        "y": 5,
        "capacity": 5,
        "items": []
      },
      {
        "x": 19,
        "y": 5,
        "capacity": 5,
        "items": []
      },
      {
        "x": 20,
        "y": 5,
        "capacity": 5,
        "items": []
      },
      {
        "x": 21,
        "y": 5,
        "capacity": 5,
        "items": []
      },
      {
        "x": 22,
        "y": 5,
        "capacity": 5,
        "items": []
      },
      {
        "x": 23,
        "y": 5,
        "capacity": 5,
        "items": []
      },
      {
        "x": 25,
        "y": 5,
        "capacity": 5,
        "items": []
      },
      {
        "x": 26,
        "y": 5,
        "capacity": 5,
        "items": []
      },
      {
        "x": 27,
        "y": 5,
        "capacity": 5,
        "items": []
      },
      {
        "x": 1,
        "y": 6,
        "capacity": 5,
        "items": []
      },
      {
        "x": 3,
        "y": 6,
        "capacity": 5,
        "items": []
      },
      {
        "x": 5,
        "y": 6,
        "capacity": 5,
        "items": []
      },
      {
        "x": 13,
        "y": 6,
        "capacity": 5,
        "items": []
      },
      {
        "x": 17,
        "y": 6,
        "capacity": 5,
        "items": []
      },
      {
        "x": 19,
        "y": 6,
        "capacity": 5,
        "items": []
      },
      {
        "x": 1,
        "y": 7,
        "capacity": 5,
        "items": []
      },
      {
        "x": 3,
        "y": 7,
        "capacity": 5,
        "items": []
      },
      {
        "x": 5,
        "y": 7,
        "capacity": 5,
        "items": []
      },
      {
        "x": 6,
        "y": 7,
        "capacity": 5,
        "items": []
      },
      {
        "x": 7,
        "y": 7,
        "capacity": 5,
        "items": []
      },
      {
        "x": 8,
        "y": 7,
        "capacity": 5,
        "items": []
      },
      {
        "x": 9,
        "y": 7,
        "capacity": 5,
        "items": []
      },
      {
        "x": 11,
        "y": 7,
        "capacity": 5,
        "items": []
      },
      {
        "x": 12,
        "y": 7,
        "capacity": 5,
        "items": []
      },
      {
        "x": 13,
        "y": 7,
        "capacity": 5,
        "items": []
      },
      {
        "x": 15,
        "y": 7,
        "capacity": 5,
        "items": []
      },
      {
        "x": 16,
        "y": 7,
        "capacity": 5,
        "items": []
      },
      {
        "x": 17,
        "y": 7,
        "capacity": 5,
        "items": []
      },
      {
        "x": 19,
        "y": 7,
        "capacity": 5,
        "items": []
      },
      {
        "x": 21,
        "y": 7,
        "capacity": 5,
        "items": []
      },
      {
        "x": 22,
        "y": 7,
        "capacity": 5,
        "items": []
      },
      {
        "x": 23,
        "y": 7,
        "capacity": 5,
        "items": []
      },
      {
        "x": 25,
        "y": 7,
        "capacity": 5,
        "items": []
      },
      {
        "x": 26,
        "y": 7,
        "capacity": 5,
        "items": []
      },
      {
        "x": 27,
        "y": 7,
        "capacity": 5,
        "items": []
      },
      {
        "x": 1,
        "y": 8,
        "capacity": 5,
        "items": []
      },
      {
        "x": 3,
        "y": 8,
        "capacity": 5,
        "items": []
      },
      {
        "x": 9,
        "y": 8,
        "capacity": 5,
        "items": []
      },
      {
        "x": 11,
        "y": 8,
        "capacity": 5,
        "items": []
      },
      {
        "x": 13,
        "y": 8,
        "capacity": 5,
        "items": []
      },
      {
        "x": 15,
        "y": 8,
        "capacity": 5,
        "items": []
      },
      {
        "x": 16,
        "y": 8,
        "capacity": 5,
        "items": []
      },
      {
        "x": 19,
        "y": 8,
        "capacity": 5,
        "items": []
      },
      {
        "x": 21,
        "y": 8,
        "capacity": 5,
        "items": []
      },
      {
        "x": 23,
        "y": 8,
        "capacity": 5,
        "items": []
      },
      {
        "x": 25,
        "y": 8,
        "capacity": 5,
        "items": []
      },
      {
        "x": 27,
        "y": 8,
        "capacity": 5,
        "items": []
      },
      {
        "x": 1,
        "y": 9,
        "capacity": 5,
        "items": []
      },
      {
        "x": 3,
        "y": 9,
        "capacity": 5,
        "items": []
      },
      {
        "x": 5,
        "y": 9,
        "capacity": 5,
        "items": [
          {
            "item_type_id": "food",
            "quantity": 140
          }
        ]
      },
      {
        "x": 7,
        "y": 9,
        "capacity": 5,
        "items": []
      },
      {
        "x": 8,
        "y": 9,
        "capacity": 5,
        "items": []
      },
      {
        "x": 9,
        "y": 9,
        "capacity": 5,
        "items": []
      },
      {
        "x": 11,
        "y": 9,
        "capacity": 5,
        "items": []
      },
      {
        "x": 13,
        "y": 9,
        "capacity": 5,
        "items": []
      },
      {
        "x": 15,
        "y": 9,
        "capacity": 5,
        "items": []
      },
      {
        "x": 16,
        "y": 9,
        "capacity": 5,
        "items": []
      },
      {
        "x": 17,
        "y": 9,
        "capacity": 5,
        "items": []
      },
      {
        "x": 19,
        "y": 9,
        "capacity": 5,
        "items": []
      },
      {
        "x": 21,
        "y": 9,
        "capacity": 5,
        "items": []
      },
      {
        "x": 23,
        "y": 9,
        "capacity": 5,
        "items": []
      },
      {
        "x": 24,
        "y": 9,
        "capacity": 5,
        "items": []
      },
      {
        "x": 25,
        "y": 9,
        "capacity": 5,
        "items": []
      },
      {
        "x": 27,
        "y": 9,
        "capacity": 5,
        "items": []
      },
      {
        "x": 1,
        "y": 10,
        "capacity": 5,
        "items": []
      },
      {
        "x": 3,
        "y": 10,
        "capacity": 5,
        "items": []
      },
      {
        "x": 5,
        "y": 10,
        "capacity": 5,
        "items": []
      },
      {
        "x": 7,
        "y": 10,
        "capacity": 5,
        "items": []
      },
      {
        "x": 11,
        "y": 10,
        "capacity": 5,
        "items": []
      },
      {
        "x": 17,
        "y": 10,
        "capacity": 5,
        "items": []
      },
      {
        "x": 19,
        "y": 10,
        "capacity": 5,
        "items": []
      },
      {
        "x": 21,
        "y": 10,
        "capacity": 5,
        "items": []
      },
      {
        "x": 27,
        "y": 10,
        "capacity": 5,
        "items": []
      },
      {
        "x": 1,
        "y": 11,
        "capacity": 5,
        "items": []
      },
      {
        "x": 3,
        "y": 11,
        "capacity": 5,
        "items": []
      },
      {
        "x": 4,
        "y": 11,
        "capacity": 5,
        "items": []
      },
      {
        "x": 5,
        "y": 11,
        "capacity": 5,
        "items": []
      },
      {
        "x": 7,
        "y": 11,
        "capacity": 5,
        "items": []
      },
      {
        "x": 9,
        "y": 11,
        "capacity": 5,
        "items": []
      },
      {
        "x": 11,
        "y": 11,
        "capacity": 5,
        "items": []
      },
      {
        "x": 12,
        "y": 11,
        "capacity": 5,
        "items": []
      },
      {
        "x": 13,
        "y": 11,
        "capacity": 5,
        "items": []
      },
      {
        "x": 14,
        "y": 11,
        "capacity": 5,
        "items": []
      },
      {
        "x": 15,
        "y": 11,
        "capacity": 5,
        "items": []
      },
      {
        "x": 16,
        "y": 11,
        "capacity": 5,
        "items": []
      },
      {
        "x": 17,
        "y": 11,
        "capacity": 5,
        "items": []
      },
      {
        "x": 19,
        "y": 11,
        "capacity": 5,
        "items": []
      },
      {
        "x": 20,
        "y": 11,
        "capacity": 5,
        "items": []
      },
      {
        "x": 21,
        "y": 11,
        "capacity": 5,
        "items": []
      },
      {
        "x": 23,
        "y": 11,
        "capacity": 5,
        "items": []
      },
      {
        "x": 24,
        "y": 11,
        "capacity": 5,
        "items": []
      },
      {
        "x": 25,
        "y": 11,
        "capacity": 5,
        "items": []
      },
      {
        "x": 26,
        "y": 11,
        "capacity": 5,
        "items": []
      },
      {
        "x": 27,
        "y": 11,
        "capacity": 5,
        "items": []
      },
      {
        "x": 1,
        "y": 12,
        "capacity": 5,
        "items": []
      },
      {
        "x": 7,
        "y": 12,
        "capacity": 5,
        "items": []
      },
      {
        "x": 9,
        "y": 12,
        "capacity": 5,
        "items": []
      },
      {
        "x": 15,
        "y": 12,
        "capacity": 5,
        "items": []
      },
      {
        "x": 21,
        "y": 12,
        "capacity": 5,
        "items": []
      },
      {
        "x": 23,
        "y": 12,
        "capacity": 5,
        "items": []
      },
      {
        "x": 27,
        "y": 12,
        "capacity": 5,
        "items": []
      },
      {
        "x": 1,
        "y": 13,
        "capacity": 5,
        "items": []
      },
      {
        "x": 2,
        "y": 13,
        "capacity": 5,
        "items": []
      },
      {
        "x": 3,
        "y": 13,
        "capacity": 5,
        "items": []
      },
      {
        "x": 5,
        "y": 13,
        "capacity": 5,
        "items": []
      },
      {
        "x": 6,
        "y": 13,
        "capacity": 5,
        "items": []
      },
      {
        "x": 7,
        "y": 13,
        "capacity": 5,
        "items": []
      },
      {
        "x": 8,
        "y": 13,
        "capacity": 5,
        "items": []
      },
      {
        "x": 9,
        "y": 13,
        "capacity": 5,
        "items": []
      },
      {
        "x": 10,
        "y": 13,
        "capacity": 5,
        "items": []
      },
      {
        "x": 11,
        "y": 13,
        "capacity": 5,
        "items": []
      },
      {
        "x": 13,
        "y": 13,
        "capacity": 5,
        "items": []
      },
      {
        "x": 14,
        "y": 13,
        "capacity": 5,
        "items": []
      },
      {
        "x": 15,
        "y": 13,
        "capacity": 5,
        "items": []
      },
      {
        "x": 16,
        "y": 13,
        "capacity": 5,
        "items": []
      },
      {
        "x": 17,
        "y": 13,
        "capacity": 5,
        "items": []
      },
      {
        "x": 18,
        "y": 13,
        "capacity": 5,
        "items": []
      },
      {
        "x": 19,
        "y": 13,
        "capacity": 5,
        "items": []
      },
      {
        "x": 21,
        "y": 13,
        "capacity": 5,
        "items": []
      },
      {
        "x": 23,
        "y": 13,
        "capacity": 5,
        "items": []
      },
      {
        "x": 25,
        "y": 13,
        "capacity": 5,
        "items": []
      },
      {
        "x": 27,
        "y": 13,
        "capacity": 5,
        "items": []
      },
      {
        "x": 3,
        "y": 14,
        "capacity": 5,
        "items": []
      },
      {
        "x": 5,
        "y": 14,
        "capacity": 5,
        "items": []
      },
      {
        "x": 13,
        "y": 14,
        "capacity": 5,
        "items": []
      },
      {
        "x": 14,
        "y": 14,
        "capacity": 5,
        "items": []
      },
      {
        "x": 15,
        "y": 14,
        "capacity": 5,
        "items": []
      },
      {
        "x": 16,
        "y": 14,
        "capacity": 5,
        "items": []
      },
      {
        "x": 17,
        "y": 14,
        "capacity": 5,
        "items": []
      },
      {
        "x": 19,
        "y": 14,
        "capacity": 5,
        "items": []
      },
      {
        "x": 23,
        "y": 14,
        "capacity": 5,
        "items": []
      },
      {
        "x": 25,
        "y": 14,
        "capacity": 5,
        "items": []
      },
      {
        "x": 27,
        "y": 14,
        "capacity": 5,
        "items": []
      },
      {
        "x": 1,
        "y": 15,
        "capacity": 5,
        "items": []
      },
      {
        "x": 2,
        "y": 15,
        "capacity": 5,
        "items": []
      },
      {
        "x": 3,
        "y": 15,
        "capacity": 5,
        "items": []
      },
      {
        "x": 5,
        "y": 15,
        "capacity": 5,
        "items": []
      },
      {
        "x": 7,
        "y": 15,
        "capacity": 5,
        "items": []
      },
      {
        "x": 8,
        "y": 15,
        "capacity": 5,
        "items": []
      },
      {
        "x": 9,
        "y": 15,
        "capacity": 5,
        "items": []
      },
      {
        "x": 10,
        "y": 15,
        "capacity": 5,
        "items": []
      },
      {
        "x": 11,
        "y": 15,
        "capacity": 5,
        "items": []
      },
      {
        "x": 12,
        "y": 15,
        "capacity": 5,
        "items": []
      },
      {
        "x": 13,
        "y": 15,
        "capacity": 5,
        "items": []
      },
      {
        "x": 14,
        "y": 15,
        "capacity": 5,
        "items": []
      },
      {
        "x": 15,
        "y": 15,
        "capacity": 999,
        "items": [],
        "spawn_id": "nest_main"
      },
      {
        "x": 16,
        "y": 15,
        "capacity": 5,
        "items": []
      },
      {
        "x": 17,
        "y": 15,
        "capacity": 5,
        "items": []
      },
      {
        "x": 18,
        "y": 15,
        "capacity": 5,
        "items": []
      },
      {
        "x": 19,
        "y": 15,
        "capacity": 5,
        "items": []
      },
      {
        "x": 20,
        "y": 15,
        "capacity": 5,
        "items": []
      },
      {
        "x": 21,
        "y": 15,
        "capacity": 5,
        "items": []
      },
      {
        "x": 22,
        "y": 15,
        "capacity": 5,
        "items": []
      },
      {
        "x": 23,
        "y": 15,
        "capacity": 5,
        "items": []
      },
      {
        "x": 25,
        "y": 15,
        "capacity": 5,
        "items": []
      },
      {
        "x": 26,
        "y": 15,
        "capacity": 5,
        "items": []
      },
      {
        "x": 27,
        "y": 15,
        "capacity": 5,
        "items": []
      },
      {
        "x": 1,
        "y": 16,
        "capacity": 5,
        "items": []
      },
      {
        "x": 5,
        "y": 16,
        "capacity": 5,
        "items": []
      },
      {
        "x": 7,
        "y": 16,
        "capacity": 5,
        "items": []
      },
      {
        "x": 13,
        "y": 16,
        "capacity": 5,
        "items": []
      },
      {
        "x": 14,
        "y": 16,
        "capacity": 5,
        "items": []
      },
      {
        "x": 15,
        "y": 16,
        "capacity": 5,
        "items": []
      },
      {
        "x": 16,
        "y": 16,
        "capacity": 5,
        "items": []
      },
      {
        "x": 17,
        "y": 16,
        "capacity": 5,
        "items": []
      },
      {
        "x": 1,
        "y": 17,
        "capacity": 5,
        "items": []
      },
      {
        "x": 2,
        "y": 17,
        "capacity": 5,
        "items": []
      },
      {
        "x": 3,
        "y": 17,
        "capacity": 5,
        "items": []
      },
      {
        "x": 4,
        "y": 17,
        "capacity": 5,
        "items": []
      },
      {
        "x": 5,
        "y": 17,
        "capacity": 5,
        "items": []
      },
      {
        "x": 7,
        "y": 17,
        "capacity": 5,
        "items": []
      },
      {
        "x": 9,
        "y": 17,
        "capacity": 5,
        "items": []
      },
      {
        "x": 10,
        "y": 17,
        "capacity": 5,
        "items": []
      },
      {
        "x": 11,
        "y": 17,
        "capacity": 5,
        "items": []
      },
      {
        "x": 13,
        "y": 17,
        "capacity": 5,
        "items": []
      },
      {
        "x": 14,
        "y": 17,
        "capacity": 5,
        "items": []
      },
      {
        "x": 15,
        "y": 17,
        "capacity": 5,
        "items": []
      },
      {
        "x": 16,
        "y": 17,
        "capacity": 5,
        "items": []
      },
      {
        "x": 17,
        "y": 17,
        "capacity": 5,
        "items": []
      },
      {
        "x": 18,
        "y": 17,
        "capacity": 5,
        "items": []
      },
      {
        "x": 19,
        "y": 17,
        "capacity": 5,
        "items": []
      },
      {
        "x": 21,
        "y": 17,
        "capacity": 5,
        "items": []
      },
      {
        "x": 22,
        "y": 17,
        "capacity": 5,
        "items": []
      },
      {
        "x": 23,
        "y": 17,
        "capacity": 5,
        "items": []
      },
      {
        "x": 24,
        "y": 17,
        "capacity": 5,
        "items": []
      },
      {
        "x": 25,
        "y": 17,
        "capacity": 5,
        "items": []
      },
      {
        "x": 26,
        "y": 17,
        "capacity": 5,
        "items": []
      },
      {
        "x": 27,
        "y": 17,
        "capacity": 5,
        "items": []
      },
      {
        "x": 1,
        "y": 18,
        "capacity": 5,
        "items": []
      },
      {
        "x": 7,
        "y": 18,
        "capacity": 5,
        "items": []
      },
      {
        "x": 9,
        "y": 18,
        "capacity": 5,
        "items": []
      },
      {
        "x": 13,
        "y": 18,
        "capacity": 5,
        "items": []
      },
      {
        "x": 15,
        "y": 18,
        "capacity": 5,
        "items": []
      },
      {
        "x": 19,
        "y": 18,
        "capacity": 5,
        "items": []
      },
      {
        "x": 21,
        "y": 18,
        "capacity": 5,
        "items": []
      },
      {
        "x": 27,
        "y": 18,
        "capacity": 5,
        "items": []
      },
      {
        "x": 1,
        "y": 19,
        "capacity": 5,
        "items": []
      },
      {
        "x": 3,
        "y": 19,
        "capacity": 5,
        "items": []
      },
      {
        "x": 4,
        "y": 19,
        "capacity": 5,
        "items": []
      },
      {
        "x": 5,
        "y": 19,
        "capacity": 5,
        "items": []
      },
      {
        "x": 7,
        "y": 19,
        "capacity": 5,
        "items": []
      },
      {
        "x": 9,
        "y": 19,
        "capacity": 5,
        "items": []
      },
      {
        "x": 11,
        "y": 19,
        "capacity": 5,
        "items": []
      },
      {
        "x": 12,
        "y": 19,
        "capacity": 5,
        "items": []
      },
      {
        "x": 13,
        "y": 19,
        "capacity": 5,
        "items": []
      },
      {
        "x": 15,
        "y": 19,
        "capacity": 5,
        "items": []
      },
      {
        "x": 16,
        "y": 19,
        "capacity": 5,
        "items": []
      },
      {
        "x": 17,
        "y": 19,
        "capacity": 5,
        "items": []
      },
      {
        "x": 19,
        "y": 19,
        "capacity": 5,
        "items": []
      },
      {
        "x": 20,
        "y": 19,
        "capacity": 5,
        "items": []
      },
      {
        "x": 21,
        "y": 19,
        "capacity": 5,
        "items": []
      },
      {
        "x": 23,
        "y": 19,
        "capacity": 5,
        "items": []
      },
      {
        "x": 24,
        "y": 19,
        "capacity": 5,
        "items": []
      },
      {
        "x": 25,
        "y": 19,
        "capacity": 5,
        "items": []
      },
      {
        "x": 26,
        "y": 19,
        "capacity": 5,
        "items": []
      },
      {
        "x": 27,
        "y": 19,
        "capacity": 5,
        "items": []
      },
      {
        "x": 1,
        "y": 20,
        "capacity": 5,
        "items": []
      },
      {
        "x": 5,
        "y": 20,
        "capacity": 5,
        "items": []
      },
      {
        "x": 7,
        "y": 20,
        "capacity": 5,
        "items": []
      },
      {
        "x": 9,
        "y": 20,
        "capacity": 5,
        "items": []
      },
      {
        "x": 11,
        "y": 20,
        "capacity": 5,
        "items": []
      },
      {
        "x": 17,
        "y": 20,
        "capacity": 5,
        "items": []
      },
      {
        "x": 23,
        "y": 20,
        "capacity": 5,
        "items": []
      },
      {
        "x": 1,
        "y": 21,
        "capacity": 5,
        "items": []
      },
      {
        "x": 3,
        "y": 21,
        "capacity": 5,
        "items": []
      },
      {
        "x": 4,
        "y": 21,
        "capacity": 5,
        "items": []
      },
      {
        "x": 5,
        "y": 21,
        "capacity": 5,
        "items": []
      },
      {
        "x": 7,
        "y": 21,
        "capacity": 5,
        "items": []
      },
      {
        "x": 9,
        "y": 21,
        "capacity": 5,
        "items": []
      },
      {
        "x": 11,
        "y": 21,
        "capacity": 5,
        "items": []
      },
      {
        "x": 13,
        "y": 21,
        "capacity": 5,
        "items": []
      },
      {
        "x": 14,
        "y": 21,
        "capacity": 5,
        "items": []
      },
      {
        "x": 15,
        "y": 21,
        "capacity": 5,
        "items": []
      },
      {
        "x": 16,
        "y": 21,
        "capacity": 5,
        "items": []
      },
      {
        "x": 17,
        "y": 21,
        "capacity": 5,
        "items": []
      },
      {
        "x": 19,
        "y": 21,
        "capacity": 5,
        "items": []
      },
      {
        "x": 20,
        "y": 21,
        "capacity": 5,
        "items": []
      },
      {
        "x": 21,
        "y": 21,
        "capacity": 5,
        "items": []
      },
      {
        "x": 23,
        "y": 21,
        "capacity": 5,
        "items": []
      },
      {
        "x": 25,
        "y": 21,
        "capacity": 5,
        "items": []
      },
      {
        "x": 26,
        "y": 21,
        "capacity": 5,
        "items": []
      },
      {
        "x": 27,
        "y": 21,
        "capacity": 5,
        "items": []
      },
      {
        "x": 1,
        "y": 22,
        "capacity": 5,
        "items": []
      },
      {
        "x": 3,
        "y": 22,
        "capacity": 5,
        "items": []
      },
      {
        "x": 7,
        "y": 22,
        "capacity": 5,
        "items": []
      },
      {
        "x": 9,
        "y": 22,
        "capacity": 5,
        "items": []
      },
      {
        "x": 11,
        "y": 22,
        "capacity": 5,
        "items": []
      },
      {
        "x": 13,
        "y": 22,
        "capacity": 5,
        "items": []
      },
      {
        "x": 16,
        "y": 22,
        "capacity": 5,
        "items": []
      },
      {
        "x": 17,
        "y": 22,
        "capacity": 5,
        "items": []
      },
      {
        "x": 21,
        "y": 22,
        "capacity": 5,
        "items": []
      },
      {
        "x": 23,
        "y": 22,
        "capacity": 5,
        "items": []
      },
      {
        "x": 27,
        "y": 22,
        "capacity": 5,
        "items": []
      },
      {
        "x": 1,
        "y": 23,
        "capacity": 5,
        "items": []
      },
      {
        "x": 2,
        "y": 23,
        "capacity": 5,
        "items": []
      },
      {
        "x": 3,
        "y": 23,
        "capacity": 5,
        "items": []
      },
      {
        "x": 5,
        "y": 23,
        "capacity": 5,
        "items": []
      },
      {
        "x": 6,
        "y": 23,
        "capacity": 5,
        "items": []
      },
      {
        "x": 7,
        "y": 23,
        "capacity": 5,
        "items": []
      },
      {
        "x": 9,
        "y": 23,
        "capacity": 5,
        "items": []
      },
      {
        "x": 10,
        "y": 23,
        "capacity": 5,
        "items": []
      },
      {
        "x": 11,
        "y": 23,
        "capacity": 5,
        "items": []
      },
      {
        "x": 12,
        "y": 23,
        "capacity": 5,
        "items": []
      },
      {
        "x": 13,
        "y": 23,
        "capacity": 5,
        "items": []
      },
      {
        "x": 15,
        "y": 23,
        "capacity": 5,
        "items": []
      },
      {
        "x": 16,
        "y": 23,
        "capacity": 5,
        "items": []
      },
      {
        "x": 17,
        "y": 23,
        "capacity": 5,
        "items": []
      },
      {
        "x": 18,
        "y": 23,
        "capacity": 5,
        "items": []
      },
      {
        "x": 19,
        "y": 23,
        "capacity": 5,
        "items": []
      },
      {
        "x": 21,
        "y": 23,
        "capacity": 5,
        "items": []
      },
      {
        "x": 23,
        "y": 23,
        "capacity": 5,
        "items": []
      },
      {
        "x": 24,
        "y": 23,
        "capacity": 5,
        "items": []
      },
      {
        "x": 25,
        "y": 23,
        "capacity": 5,
        "items": []
      },
      {
        "x": 26,
        "y": 23,
        "capacity": 5,
        "items": []
      },
      {
        "x": 27,
        "y": 23,
        "capacity": 5,
        "items": []
      },
      {
        "x": 3,
        "y": 24,
        "capacity": 5,
        "items": []
      },
      {
        "x": 5,
        "y": 24,
        "capacity": 5,
        "items": []
      },
      {
        "x": 19,
        "y": 24,
        "capacity": 5,
        "items": []
      },
      {
        "x": 21,
        "y": 24,
        "capacity": 5,
        "items": []
      },
      {
        "x": 27,
        "y": 24,
        "capacity": 5,
        "items": []
      },
      {
        "x": 1,
        "y": 25,
        "capacity": 5,
        "items": [
          {
            "item_type_id": "food",
            "quantity": 120
          }
        ]
      },
      {
        "x": 3,
        "y": 25,
        "capacity": 5,
        "items": []
      },
      {
        "x": 5,
        "y": 25,
        "capacity": 5,
        "items": []
      },
      {
        "x": 6,
        "y": 25,
        "capacity": 5,
        "items": []
      },
      {
        "x": 7,
        "y": 25,
        "capacity": 5,
        "items": []
      },
      {
        "x": 8,
        "y": 25,
        "capacity": 5,
        "items": []
      },
      {
        "x": 9,
        "y": 25,
        "capacity": 5,
        "items": []
      },
      {
        "x": 11,
        "y": 25,
        "capacity": 5,
        "items": []
      },
      {
        "x": 12,
        "y": 25,
        "capacity": 5,
        "items": []
      },
      {
        "x": 13,
        "y": 25,
        "capacity": 5,
        "items": []
      },
      {
        "x": 14,
        "y": 25,
        "capacity": 5,
        "items": []
      },
      {
        "x": 15,
        "y": 25,
        "capacity": 5,
        "items": []
      },
      {
        "x": 16,
        "y": 25,
        "capacity": 5,
        "items": []
      },
      {
        "x": 17,
        "y": 25,
        "capacity": 5,
        "items": []
      },
      {
        "x": 19,
        "y": 25,
        "capacity": 5,
        "items": []
      },
      {
        "x": 20,
        "y": 25,
        "capacity": 5,
        "items": []
      },
      {
        "x": 21,
        "y": 25,
        "capacity": 5,
        "items": []
      },
      {
        "x": 22,
        "y": 25,
        "capacity": 5,
        "items": []
      },
      {
        "x": 23,
        "y": 25,
        "capacity": 5,
        "items": []
      },
      {
        "x": 24,
        "y": 25,
        "capacity": 5,
        "items": []
      },
      {
        "x": 25,
        "y": 25,
        "capacity": 5,
        "items": []
      },
      {
        "x": 27,
        "y": 25,
        "capacity": 5,
        "items": []
      },
      {
        "x": 1,
        "y": 26,
        "capacity": 5,
        "items": []
      },
      {
        "x": 3,
        "y": 26,
        "capacity": 5,
        "items": []
      },
      {
        "x": 9,
        "y": 26,
        "capacity": 5,
        "items": []
      },
      {
        "x": 11,
        "y": 26,
        "capacity": 5,
        "items": []
      },
      {
        "x": 17,
        "y": 26,
        "capacity": 5,
        "items": []
      },
      {
        "x": 27,
        "y": 26,
        "capacity": 5,
        "items": []
      },
      {
        "x": 1,
        "y": 27,
        "capacity": 5,
        "items": []
      },
      {
        "x": 2,
        "y": 27,
        "capacity": 5,
        "items": []
      },
      {
        "x": 3,
        "y": 27,
        "capacity": 5,
        "items": []
      },
      {
        "x": 4,
        "y": 27,
        "capacity": 5,
        "items": []
      },
      {
        "x": 5,
        "y": 27,
        "capacity": 5,
        "items": []
      },
      {
        "x": 6,
        "y": 27,
        "capacity": 5,
        "items": []
      },
      {
        "x": 7,
        "y": 27,
        "capacity": 5,
        "items": [
          {
            "item_type_id": "food",
            "quantity": 130
          }
        ]
      },
      {
        "x": 9,
        "y": 27,
        "capacity": 5,
        "items": []
      },
      {
        "x": 10,
        "y": 27,
        "capacity": 5,
        "items": []
      },
      {
        "x": 11,
        "y": 27,
        "capacity": 5,
        "items": []
      },
      {
        "x": 12,
        "y": 27,
        "capacity": 5,
        "items": []
      },
      {
        "x": 13,
        "y": 27,
        "capacity": 5,
        "items": []
      },
      {
        "x": 14,
        "y": 27,
        "capacity": 5,
        "items": []
      },
      {
        "x": 15,
        "y": 27,
        "capacity": 5,
        "items": []
      },
      {
        "x": 17,
        "y": 27,
        "capacity": 5,
        "items": []
      },
      {
        "x": 18,
        "y": 27,
        "capacity": 5,
        "items": []
      },
      {
        "x": 19,
        "y": 27,
        "capacity": 5,
        "items": []
      },
      {
        "x": 20,
        "y": 27,
        "capacity": 5,
        "items": []
      },
      {
        "x": 21,
        "y": 27,
        "capacity": 5,
        "items": []
      },
      {
        "x": 22,
        "y": 27,
        "capacity": 5,
        "items": []
      },
      {
        "x": 23,
        "y": 27,
        "capacity": 5,
        "items": []
      },
      {
        "x": 24,
        "y": 27,
        "capacity": 5,
        "items": []
      },
      {
        "x": 25,
        "y": 27,
        "capacity": 5,
        "items": []
      },
      {
        "x": 26,
        "y": 27,
        "capacity": 5,
        "items": []
      },
      {
        "x": 27,
        "y": 27,
        "capacity": 5,
        "items": []
      }
    ]
  },
  "logging": {
    "events": [
      "food_found",
      "food_delivered",
      "agent_death",
      "tick_summary"
    ],
    "grid_state_every_n_ticks": 8,
    "tick_summary_every_n_ticks": 2
  },
  "simulations": [
    {
      "id": "sim_15ants",
      "name": "15 Ameisen",
      "spawns": [
        {
          "id": "nest_main",
          "name": "Hauptnest",
          "agent_spawns": [
            {
              "agent_type_id": "ant",
              "count": 15
            }
          ]
        }
      ]
    },
    {
      "id": "sim_25ants",
      "name": "25 Ameisen",
      "spawns": [
        {
          "id": "nest_main",
          "name": "Hauptnest",
          "agent_spawns": [
            {
              "agent_type_id": "ant",
              "count": 25
            }
          ]
        }
      ]
    },
    {
      "id": "sim_35ants",
      "name": "35 Ameisen",
      "spawns": [
        {
          "id": "nest_main",
          "name": "Hauptnest",
          "agent_spawns": [
            {
              "agent_type_id": "ant",
              "count": 35
            }
          ]
        }
      ]
    }
  ]
}
